patsemb/__init__.py
patsemb/discretization/Discretizer.py
patsemb/discretization/SAXDiscretizer.py
patsemb/discretization/__init__.py
patsemb/pattern_based_embedding/PatternBasedEmbedder.py
patsemb/pattern_based_embedding/__init__.py
patsemb/pattern_based_embedding/visualization.py
patsemb/pattern_mining/PatternMiner.py
patsemb/pattern_mining/__init__.py
patsemb/pattern_mining/SPMF/NOSEP.py
patsemb/pattern_mining/SPMF/QCSP.py
patsemb/pattern_mining/SPMF/SPMF.py
patsemb/pattern_mining/SPMF/__init__.py
patsemb/pattern_mining/SPMF/spmf.jar
patsemb/postprocess/Postprocessor.py
patsemb/postprocess/Smoother.py
patsemb/postprocess/__init__.py
patsemb/utils/__init__.py
patsemb/utils/handle_datetime.py
patsemb-0.1.1.dist-info/AUTHORS
patsemb-0.1.1.dist-info/LICENSE
patsemb-0.1.1.dist-info/METADATA
patsemb-0.1.1.dist-info/WHEEL
patsemb-0.1.1.dist-info/top_level.txt
patsemb-0.1.1.dist-info/RECORD
