Metadata-Version: 2.1
Name: patsemb
Version: 0.1.1
Summary: PaTSEmb: Pattern-based Time Series Embedding
Author-email: Louis Carpentier <louis.carpentier@kuleuven.be>
License: MIT License
Project-URL: homepage, https://pypi.org/project/patsemb/
Project-URL: repository, https://gitlab.kuleuven.be/m-group-campus-brugge/dtai_public/patsemb
Project-URL: changelog, https://gitlab.kuleuven.be/m-group-campus-brugge/dtai_public/patsemb/-/blob/main/CHANGELOG.md
Project-URL: documentation, https://patsemb-u0143709-3a07c9d27a51b62b1b2bad2f623ad154a9a19db833f1f7.pages.gitlab.kuleuven.be/
Keywords: machine-learning,time-series,semantic-segmentation,data-mining
Classifier: Development Status :: 3 - Alpha
Classifier: License :: OSI Approved :: MIT License
Classifier: Programming Language :: Python :: 3.8
Classifier: Programming Language :: Python :: 3.9
Classifier: Programming Language :: Python :: 3.10
Classifier: Programming Language :: Python :: 3.11
Classifier: Programming Language :: Python :: 3.12
Requires-Python: <=3.12,>=3.8
License-File: LICENSE
License-File: AUTHORS
Requires-Dist: numpy>=1.22
Requires-Dist: scipy>=1.10
Requires-Dist: scikit-learn>=1.3
Requires-Dist: numba>=0.58
Requires-Dist: matplotlib>=3.7
